nanochat-0.1.2.dist-info/METADATA
nanochat-0.1.2.dist-info/WHEEL
nanochat-0.1.2.dist-info/licenses/LICENSE
rustbpe/__init__.py
rustbpe/rustbpe.cpython-310-darwin.so
nanochat-0.1.2.dist-info/RECORD
