Metadata-Version: 2.4
Name: nanochat
Version: 0.1.2
Requires-Dist: datasets>=4.0.0
Requires-Dist: fastapi>=0.117.1
Requires-Dist: files-to-prompt>=0.6
Requires-Dist: numpy==1.26.4
Requires-Dist: psutil>=7.1.0
Requires-Dist: regex>=2025.9.1
Requires-Dist: tiktoken>=0.11.0
Requires-Dist: tokenizers>=0.22.0
Requires-Dist: torch>=2.0.0
Requires-Dist: uvicorn>=0.36.0
Requires-Dist: wandb>=0.21.3
License-File: LICENSE
Summary: the minimal full-stack ChatGPT clone
Author: Andrej Karpathy
Maintainer: Sermet Pekin
Requires-Python: >=3.9
